LICENSE
README.md
README.rst
setup.py
keyhub/__init__.py
keyhub/account.py
keyhub/authentication.py
keyhub/client.py
keyhub/misc.py
keyhub/profile.py
keyhub/vault.py
keyhub.egg-info/PKG-INFO
keyhub.egg-info/SOURCES.txt
keyhub.egg-info/dependency_links.txt
keyhub.egg-info/not-zip-safe
keyhub.egg-info/requires.txt
keyhub.egg-info/top_level.txt